pynetrees/__init__.py
pynetrees/cashflow.py
pynetrees/decision.py
pynetrees/endgame.py
pynetrees/evaluator.py
pynetrees/event.py
pynetrees/jupyter.py
pynetrees/limits.py
pynetrees/node.py
pynetrees/render.py
pynetrees/sensitivity.py
pynetrees/solver.py
pynetrees/strategy.py
pynetrees/transition.py
pynetrees/valueactualizer.py
pynetrees-1.0.1.dist-info/WHEEL
pynetrees-1.0.1.dist-info/METADATA
pynetrees-1.0.1.dist-info/RECORD
